pytest_eliot/__init__.py
pytest_eliot/plugin.py
pytest_eliot-0.0.3.dist-info/LICENSE
pytest_eliot-0.0.3.dist-info/METADATA
pytest_eliot-0.0.3.dist-info/WHEEL
pytest_eliot-0.0.3.dist-info/entry_points.txt
pytest_eliot-0.0.3.dist-info/top_level.txt
pytest_eliot-0.0.3.dist-info/RECORD
